{
  "frames": {
    "004.png": {
      "frame": {
        "x": 0,
        "y": 0,
        "w": 128,
        "h": 128
      },
      "rotated": false,
      "trimmed": false,
      "spriteSourceSize": {
        "x": 0,
        "y": 0,
        "w": 128,
        "h": 128
      },
      "sourceSize": {
        "w": 128,
        "h": 128
      },
      "pivot": {
        "x": 0.5,
        "y": 0.5
      }
    },
    "attack-6.png": {
      "frame": {
        "x": 0,
        "y": 128,
        "w": 44,
        "h": 118
      },
      "rotated": false,
      "trimmed": true,
      "spriteSourceSize": {
        "x": 42,
        "y": 10,
        "w": 44,
        "h": 118
      },
      "sourceSize": {
        "w": 128,
        "h": 128
      },
      "pivot": {
        "x": 0.5,
        "y": 0.5
      }
    },
    "attack-7.png": {
      "frame": {
        "x": 0,
        "y": 246,
        "w": 50,
        "h": 98
      },
      "rotated": false,
      "trimmed": true,
      "spriteSourceSize": {
        "x": 38,
        "y": 0,
        "w": 50,
        "h": 98
      },
      "sourceSize": {
        "w": 128,
        "h": 128
      },
      "pivot": {
        "x": 0.5,
        "y": 0.5
      }
    },
    "035.png": {
      "frame": {
        "x": 44,
        "y": 128,
        "w": 70,
        "h": 92
      },
      "rotated": false,
      "trimmed": true,
      "spriteSourceSize": {
        "x": 28,
        "y": 28,
        "w": 70,
        "h": 92
      },
      "sourceSize": {
        "w": 128,
        "h": 128
      },
      "pivot": {
        "x": 0.5,
        "y": 0.5
      }
    },
    "038.png": {
      "frame": {
        "x": 0,
        "y": 344,
        "w": 68,
        "h": 90
      },
      "rotated": false,
      "trimmed": true,
      "spriteSourceSize": {
        "x": 30,
        "y": 38,
        "w": 68,
        "h": 90
      },
      "sourceSize": {
        "w": 128,
        "h": 128
      },
      "pivot": {
        "x": 0.5,
        "y": 0.5
      }
    },
    "walking-6.png": {
      "frame": {
        "x": 50,
        "y": 220,
        "w": 68,
        "h": 90
      },
      "rotated": false,
      "trimmed": true,
      "spriteSourceSize": {
        "x": 30,
        "y": 38,
        "w": 68,
        "h": 90
      },
      "sourceSize": {
        "w": 128,
        "h": 128
      },
      "pivot": {
        "x": 0.5,
        "y": 0.5
      }
    },
    "death-10.png": {
      "frame": {
        "x": 50,
        "y": 310,
        "w": 72,
        "h": 34
      },
      "rotated": false,
      "trimmed": true,
      "spriteSourceSize": {
        "x": 26,
        "y": 94,
        "w": 72,
        "h": 34
      },
      "sourceSize": {
        "w": 128,
        "h": 128
      },
      "pivot": {
        "x": 0.5,
        "y": 0.5
      }
    },
    "walking-3.png": {
      "frame": {
        "x": 114,
        "y": 128,
        "w": 60,
        "h": 90
      },
      "rotated": false,
      "trimmed": true,
      "spriteSourceSize": {
        "x": 34,
        "y": 38,
        "w": 60,
        "h": 90
      },
      "sourceSize": {
        "w": 128,
        "h": 128
      },
      "pivot": {
        "x": 0.5,
        "y": 0.5
      }
    },
    "walking-2.png": {
      "frame": {
        "x": 118,
        "y": 218,
        "w": 68,
        "h": 88
      },
      "rotated": false,
      "trimmed": true,
      "spriteSourceSize": {
        "x": 30,
        "y": 40,
        "w": 68,
        "h": 88
      },
      "sourceSize": {
        "w": 128,
        "h": 128
      },
      "pivot": {
        "x": 0.5,
        "y": 0.5
      }
    },
    "walking-5.png": {
      "frame": {
        "x": 128,
        "y": 0,
        "w": 66,
        "h": 88
      },
      "rotated": false,
      "trimmed": true,
      "spriteSourceSize": {
        "x": 30,
        "y": 40,
        "w": 66,
        "h": 88
      },
      "sourceSize": {
        "w": 128,
        "h": 128
      },
      "pivot": {
        "x": 0.5,
        "y": 0.5
      }
    },
    "death-8.png": {
      "frame": {
        "x": 128,
        "y": 88,
        "w": 72,
        "h": 40
      },
      "rotated": false,
      "trimmed": true,
      "spriteSourceSize": {
        "x": 26,
        "y": 88,
        "w": 72,
        "h": 40
      },
      "sourceSize": {
        "w": 128,
        "h": 128
      },
      "pivot": {
        "x": 0.5,
        "y": 0.5
      }
    },
    "094.png": {
      "frame": {
        "x": 194,
        "y": 0,
        "w": 92,
        "h": 84
      },
      "rotated": false,
      "trimmed": true,
      "spriteSourceSize": {
        "x": 30,
        "y": 44,
        "w": 92,
        "h": 84
      },
      "sourceSize": {
        "w": 128,
        "h": 128
      },
      "pivot": {
        "x": 0.5,
        "y": 0.5
      }
    },
    "065.png": {
      "frame": {
        "x": 174,
        "y": 128,
        "w": 74,
        "h": 84
      },
      "rotated": false,
      "trimmed": true,
      "spriteSourceSize": {
        "x": 26,
        "y": 44,
        "w": 74,
        "h": 84
      },
      "sourceSize": {
        "w": 128,
        "h": 128
      },
      "pivot": {
        "x": 0.5,
        "y": 0.5
      }
    },
    "death-11.png": {
      "frame": {
        "x": 200,
        "y": 84,
        "w": 72,
        "h": 34
      },
      "rotated": false,
      "trimmed": true,
      "spriteSourceSize": {
        "x": 26,
        "y": 94,
        "w": 72,
        "h": 34
      },
      "sourceSize": {
        "w": 128,
        "h": 128
      },
      "pivot": {
        "x": 0.5,
        "y": 0.5
      }
    },
    "036.png": {
      "frame": {
        "x": 0,
        "y": 434,
        "w": 72,
        "h": 84
      },
      "rotated": false,
      "trimmed": true,
      "spriteSourceSize": {
        "x": 26,
        "y": 24,
        "w": 72,
        "h": 84
      },
      "sourceSize": {
        "w": 128,
        "h": 128
      },
      "pivot": {
        "x": 0.5,
        "y": 0.5
      }
    },
    "037.png": {
      "frame": {
        "x": 68,
        "y": 344,
        "w": 70,
        "h": 84
      },
      "rotated": false,
      "trimmed": true,
      "spriteSourceSize": {
        "x": 28,
        "y": 22,
        "w": 70,
        "h": 84
      },
      "sourceSize": {
        "w": 128,
        "h": 128
      },
      "pivot": {
        "x": 0.5,
        "y": 0.5
      }
    },
    "death-9.png": {
      "frame": {
        "x": 122,
        "y": 306,
        "w": 72,
        "h": 34
      },
      "rotated": false,
      "trimmed": true,
      "spriteSourceSize": {
        "x": 26,
        "y": 94,
        "w": 72,
        "h": 34
      },
      "sourceSize": {
        "w": 128,
        "h": 128
      },
      "pivot": {
        "x": 0.5,
        "y": 0.5
      }
    },
    "130.png": {
      "frame": {
        "x": 186,
        "y": 212,
        "w": 70,
        "h": 84
      },
      "rotated": false,
      "trimmed": true,
      "spriteSourceSize": {
        "x": 30,
        "y": 44,
        "w": 70,
        "h": 84
      },
      "sourceSize": {
        "w": 128,
        "h": 128
      },
      "pivot": {
        "x": 0.5,
        "y": 0.5
      }
    },
    "132.png": {
      "frame": {
        "x": 248,
        "y": 118,
        "w": 70,
        "h": 84
      },
      "rotated": false,
      "trimmed": true,
      "spriteSourceSize": {
        "x": 30,
        "y": 44,
        "w": 70,
        "h": 84
      },
      "sourceSize": {
        "w": 128,
        "h": 128
      },
      "pivot": {
        "x": 0.5,
        "y": 0.5
      }
    },
    "066.png": {
      "frame": {
        "x": 286,
        "y": 0,
        "w": 68,
        "h": 84
      },
      "rotated": false,
      "trimmed": true,
      "spriteSourceSize": {
        "x": 24,
        "y": 44,
        "w": 68,
        "h": 84
      },
      "sourceSize": {
        "w": 128,
        "h": 128
      },
      "pivot": {
        "x": 0.5,
        "y": 0.5
      }
    },
    "081.png": {
      "frame": {
        "x": 0,
        "y": 518,
        "w": 68,
        "h": 84
      },
      "rotated": false,
      "trimmed": true,
      "spriteSourceSize": {
        "x": 30,
        "y": 44,
        "w": 68,
        "h": 84
      },
      "sourceSize": {
        "w": 128,
        "h": 128
      },
      "pivot": {
        "x": 0.5,
        "y": 0.5
      }
    },
    "idle-1.png": {
      "frame": {
        "x": 0,
        "y": 602,
        "w": 68,
        "h": 84
      },
      "rotated": false,
      "trimmed": true,
      "spriteSourceSize": {
        "x": 30,
        "y": 44,
        "w": 68,
        "h": 84
      },
      "sourceSize": {
        "w": 128,
        "h": 128
      },
      "pivot": {
        "x": 0.5,
        "y": 0.5
      }
    },
    "idle-4.png": {
      "frame": {
        "x": 0,
        "y": 686,
        "w": 68,
        "h": 84
      },
      "rotated": false,
      "trimmed": true,
      "spriteSourceSize": {
        "x": 30,
        "y": 44,
        "w": 68,
        "h": 84
      },
      "sourceSize": {
        "w": 128,
        "h": 128
      },
      "pivot": {
        "x": 0.5,
        "y": 0.5
      }
    },
    "052.png": {
      "frame": {
        "x": 0,
        "y": 770,
        "w": 76,
        "h": 82
      },
      "rotated": false,
      "trimmed": true,
      "spriteSourceSize": {
        "x": 30,
        "y": 46,
        "w": 76,
        "h": 82
      },
      "sourceSize": {
        "w": 128,
        "h": 128
      },
      "pivot": {
        "x": 0.5,
        "y": 0.5
      }
    },
    "053.png": {
      "frame": {
        "x": 68,
        "y": 518,
        "w": 76,
        "h": 82
      },
      "rotated": false,
      "trimmed": true,
      "spriteSourceSize": {
        "x": 30,
        "y": 46,
        "w": 76,
        "h": 82
      },
      "sourceSize": {
        "w": 128,
        "h": 128
      },
      "pivot": {
        "x": 0.5,
        "y": 0.5
      }
    },
    "054.png": {
      "frame": {
        "x": 72,
        "y": 428,
        "w": 76,
        "h": 82
      },
      "rotated": false,
      "trimmed": true,
      "spriteSourceSize": {
        "x": 30,
        "y": 46,
        "w": 76,
        "h": 82
      },
      "sourceSize": {
        "w": 128,
        "h": 128
      },
      "pivot": {
        "x": 0.5,
        "y": 0.5
      }
    },
    "055.png": {
      "frame": {
        "x": 144,
        "y": 340,
        "w": 76,
        "h": 82
      },
      "rotated": false,
      "trimmed": true,
      "spriteSourceSize": {
        "x": 30,
        "y": 46,
        "w": 76,
        "h": 82
      },
      "sourceSize": {
        "w": 128,
        "h": 128
      },
      "pivot": {
        "x": 0.5,
        "y": 0.5
      }
    },
    "056.png": {
      "frame": {
        "x": 148,
        "y": 422,
        "w": 76,
        "h": 82
      },
      "rotated": false,
      "trimmed": true,
      "spriteSourceSize": {
        "x": 30,
        "y": 46,
        "w": 76,
        "h": 82
      },
      "sourceSize": {
        "w": 128,
        "h": 128
      },
      "pivot": {
        "x": 0.5,
        "y": 0.5
      }
    },
    "057.png": {
      "frame": {
        "x": 220,
        "y": 296,
        "w": 76,
        "h": 82
      },
      "rotated": false,
      "trimmed": true,
      "spriteSourceSize": {
        "x": 30,
        "y": 46,
        "w": 76,
        "h": 82
      },
      "sourceSize": {
        "w": 128,
        "h": 128
      },
      "pivot": {
        "x": 0.5,
        "y": 0.5
      }
    },
    "058.png": {
      "frame": {
        "x": 256,
        "y": 202,
        "w": 76,
        "h": 82
      },
      "rotated": false,
      "trimmed": true,
      "spriteSourceSize": {
        "x": 30,
        "y": 46,
        "w": 76,
        "h": 82
      },
      "sourceSize": {
        "w": 128,
        "h": 128
      },
      "pivot": {
        "x": 0.5,
        "y": 0.5
      }
    },
    "129.png": {
      "frame": {
        "x": 318,
        "y": 84,
        "w": 70,
        "h": 82
      },
      "rotated": false,
      "trimmed": true,
      "spriteSourceSize": {
        "x": 30,
        "y": 46,
        "w": 70,
        "h": 82
      },
      "sourceSize": {
        "w": 128,
        "h": 128
      },
      "pivot": {
        "x": 0.5,
        "y": 0.5
      }
    },
    "131.png": {
      "frame": {
        "x": 354,
        "y": 0,
        "w": 70,
        "h": 82
      },
      "rotated": false,
      "trimmed": true,
      "spriteSourceSize": {
        "x": 30,
        "y": 46,
        "w": 70,
        "h": 82
      },
      "sourceSize": {
        "w": 128,
        "h": 128
      },
      "pivot": {
        "x": 0.5,
        "y": 0.5
      }
    },
    "133.png": {
      "frame": {
        "x": 68,
        "y": 600,
        "w": 70,
        "h": 82
      },
      "rotated": false,
      "trimmed": true,
      "spriteSourceSize": {
        "x": 30,
        "y": 46,
        "w": 70,
        "h": 82
      },
      "sourceSize": {
        "w": 128,
        "h": 128
      },
      "pivot": {
        "x": 0.5,
        "y": 0.5
      }
    },
    "idle-2.png": {
      "frame": {
        "x": 68,
        "y": 682,
        "w": 70,
        "h": 82
      },
      "rotated": false,
      "trimmed": true,
      "spriteSourceSize": {
        "x": 28,
        "y": 46,
        "w": 70,
        "h": 82
      },
      "sourceSize": {
        "w": 128,
        "h": 128
      },
      "pivot": {
        "x": 0.5,
        "y": 0.5
      }
    },
    "032.png": {
      "frame": {
        "x": 0,
        "y": 852,
        "w": 68,
        "h": 82
      },
      "rotated": false,
      "trimmed": true,
      "spriteSourceSize": {
        "x": 30,
        "y": 46,
        "w": 68,
        "h": 82
      },
      "sourceSize": {
        "w": 128,
        "h": 128
      },
      "pivot": {
        "x": 0.5,
        "y": 0.5
      }
    },
    "048.png": {
      "frame": {
        "x": 0,
        "y": 934,
        "w": 68,
        "h": 82
      },
      "rotated": false,
      "trimmed": true,
      "spriteSourceSize": {
        "x": 30,
        "y": 46,
        "w": 68,
        "h": 82
      },
      "sourceSize": {
        "w": 128,
        "h": 128
      },
      "pivot": {
        "x": 0.5,
        "y": 0.5
      }
    },
    "070.png": {
      "frame": {
        "x": 0,
        "y": 1016,
        "w": 68,
        "h": 82
      },
      "rotated": false,
      "trimmed": true,
      "spriteSourceSize": {
        "x": 30,
        "y": 46,
        "w": 68,
        "h": 82
      },
      "sourceSize": {
        "w": 128,
        "h": 128
      },
      "pivot": {
        "x": 0.5,
        "y": 0.5
      }
    },
    "death-2.png": {
      "frame": {
        "x": 0,
        "y": 1098,
        "w": 68,
        "h": 82
      },
      "rotated": false,
      "trimmed": true,
      "spriteSourceSize": {
        "x": 30,
        "y": 46,
        "w": 68,
        "h": 82
      },
      "sourceSize": {
        "w": 128,
        "h": 128
      },
      "pivot": {
        "x": 0.5,
        "y": 0.5
      }
    },
    "walking-1.png": {
      "frame": {
        "x": 0,
        "y": 1180,
        "w": 68,
        "h": 82
      },
      "rotated": false,
      "trimmed": true,
      "spriteSourceSize": {
        "x": 30,
        "y": 46,
        "w": 68,
        "h": 82
      },
      "sourceSize": {
        "w": 128,
        "h": 128
      },
      "pivot": {
        "x": 0.5,
        "y": 0.5
      }
    },
    "walking-4.png": {
      "frame": {
        "x": 0,
        "y": 1262,
        "w": 64,
        "h": 82
      },
      "rotated": false,
      "trimmed": true,
      "spriteSourceSize": {
        "x": 28,
        "y": 46,
        "w": 64,
        "h": 82
      },
      "sourceSize": {
        "w": 128,
        "h": 128
      },
      "pivot": {
        "x": 0.5,
        "y": 0.5
      }
    },
    "093.png": {
      "frame": {
        "x": 0,
        "y": 1344,
        "w": 90,
        "h": 78
      },
      "rotated": false,
      "trimmed": true,
      "spriteSourceSize": {
        "x": 30,
        "y": 50,
        "w": 90,
        "h": 78
      },
      "sourceSize": {
        "w": 128,
        "h": 128
      },
      "pivot": {
        "x": 0.5,
        "y": 0.5
      }
    },
    "067.png": {
      "frame": {
        "x": 64,
        "y": 1262,
        "w": 76,
        "h": 78
      },
      "rotated": false,
      "trimmed": true,
      "spriteSourceSize": {
        "x": 34,
        "y": 50,
        "w": 76,
        "h": 78
      },
      "sourceSize": {
        "w": 128,
        "h": 128
      },
      "pivot": {
        "x": 0.5,
        "y": 0.5
      }
    },
    "082.png": {
      "frame": {
        "x": 68,
        "y": 852,
        "w": 70,
        "h": 78
      },
      "rotated": false,
      "trimmed": true,
      "spriteSourceSize": {
        "x": 30,
        "y": 46,
        "w": 70,
        "h": 78
      },
      "sourceSize": {
        "w": 128,
        "h": 128
      },
      "pivot": {
        "x": 0.5,
        "y": 0.5
      }
    },
    "069.png": {
      "frame": {
        "x": 76,
        "y": 764,
        "w": 68,
        "h": 78
      },
      "rotated": false,
      "trimmed": true,
      "spriteSourceSize": {
        "x": 30,
        "y": 50,
        "w": 68,
        "h": 78
      },
      "sourceSize": {
        "w": 128,
        "h": 128
      },
      "pivot": {
        "x": 0.5,
        "y": 0.5
      }
    },
    "090.png": {
      "frame": {
        "x": 138,
        "y": 600,
        "w": 68,
        "h": 78
      },
      "rotated": false,
      "trimmed": true,
      "spriteSourceSize": {
        "x": 30,
        "y": 50,
        "w": 68,
        "h": 78
      },
      "sourceSize": {
        "w": 128,
        "h": 128
      },
      "pivot": {
        "x": 0.5,
        "y": 0.5
      }
    },
    "097.png": {
      "frame": {
        "x": 138,
        "y": 678,
        "w": 68,
        "h": 78
      },
      "rotated": false,
      "trimmed": true,
      "spriteSourceSize": {
        "x": 30,
        "y": 50,
        "w": 68,
        "h": 78
      },
      "sourceSize": {
        "w": 128,
        "h": 128
      },
      "pivot": {
        "x": 0.5,
        "y": 0.5
      }
    },
    "099.png": {
      "frame": {
        "x": 144,
        "y": 510,
        "w": 68,
        "h": 78
      },
      "rotated": false,
      "trimmed": true,
      "spriteSourceSize": {
        "x": 30,
        "y": 50,
        "w": 68,
        "h": 78
      },
      "sourceSize": {
        "w": 128,
        "h": 128
      },
      "pivot": {
        "x": 0.5,
        "y": 0.5
      }
    },
    "attack-8.png": {
      "frame": {
        "x": 68,
        "y": 930,
        "w": 68,
        "h": 78
      },
      "rotated": false,
      "trimmed": true,
      "spriteSourceSize": {
        "x": 30,
        "y": 0,
        "w": 68,
        "h": 78
      },
      "sourceSize": {
        "w": 128,
        "h": 128
      },
      "pivot": {
        "x": 0.5,
        "y": 0.5
      }
    },
    "attack-9.png": {
      "frame": {
        "x": 68,
        "y": 1008,
        "w": 68,
        "h": 78
      },
      "rotated": false,
      "trimmed": true,
      "spriteSourceSize": {
        "x": 30,
        "y": 20,
        "w": 68,
        "h": 78
      },
      "sourceSize": {
        "w": 128,
        "h": 128
      },
      "pivot": {
        "x": 0.5,
        "y": 0.5
      }
    },
    "051.png": {
      "frame": {
        "x": 68,
        "y": 1086,
        "w": 66,
        "h": 78
      },
      "rotated": false,
      "trimmed": true,
      "spriteSourceSize": {
        "x": 32,
        "y": 50,
        "w": 66,
        "h": 78
      },
      "sourceSize": {
        "w": 128,
        "h": 128
      },
      "pivot": {
        "x": 0.5,
        "y": 0.5
      }
    },
    "049.png": {
      "frame": {
        "x": 68,
        "y": 1164,
        "w": 62,
        "h": 78
      },
      "rotated": false,
      "trimmed": true,
      "spriteSourceSize": {
        "x": 32,
        "y": 50,
        "w": 62,
        "h": 78
      },
      "sourceSize": {
        "w": 128,
        "h": 128
      },
      "pivot": {
        "x": 0.5,
        "y": 0.5
      }
    },
    "050.png": {
      "frame": {
        "x": 130,
        "y": 1164,
        "w": 62,
        "h": 78
      },
      "rotated": false,
      "trimmed": true,
      "spriteSourceSize": {
        "x": 30,
        "y": 50,
        "w": 62,
        "h": 78
      },
      "sourceSize": {
        "w": 128,
        "h": 128
      },
      "pivot": {
        "x": 0.5,
        "y": 0.5
      }
    },
    "098.png": {
      "frame": {
        "x": 134,
        "y": 1086,
        "w": 70,
        "h": 76
      },
      "rotated": false,
      "trimmed": true,
      "spriteSourceSize": {
        "x": 28,
        "y": 52,
        "w": 70,
        "h": 76
      },
      "sourceSize": {
        "w": 128,
        "h": 128
      },
      "pivot": {
        "x": 0.5,
        "y": 0.5
      }
    },
    "death-3.png": {
      "frame": {
        "x": 136,
        "y": 930,
        "w": 70,
        "h": 76
      },
      "rotated": false,
      "trimmed": true,
      "spriteSourceSize": {
        "x": 30,
        "y": 48,
        "w": 70,
        "h": 76
      },
      "sourceSize": {
        "w": 128,
        "h": 128
      },
      "pivot": {
        "x": 0.5,
        "y": 0.5
      }
    },
    "033.png": {
      "frame": {
        "x": 136,
        "y": 1006,
        "w": 68,
        "h": 76
      },
      "rotated": false,
      "trimmed": true,
      "spriteSourceSize": {
        "x": 30,
        "y": 52,
        "w": 68,
        "h": 76
      },
      "sourceSize": {
        "w": 128,
        "h": 128
      },
      "pivot": {
        "x": 0.5,
        "y": 0.5
      }
    },
    "034.png": {
      "frame": {
        "x": 138,
        "y": 842,
        "w": 68,
        "h": 76
      },
      "rotated": false,
      "trimmed": true,
      "spriteSourceSize": {
        "x": 30,
        "y": 52,
        "w": 68,
        "h": 76
      },
      "sourceSize": {
        "w": 128,
        "h": 128
      },
      "pivot": {
        "x": 0.5,
        "y": 0.5
      }
    },
    "attack-2.png": {
      "frame": {
        "x": 144,
        "y": 756,
        "w": 68,
        "h": 76
      },
      "rotated": false,
      "trimmed": true,
      "spriteSourceSize": {
        "x": 30,
        "y": 52,
        "w": 68,
        "h": 76
      },
      "sourceSize": {
        "w": 128,
        "h": 128
      },
      "pivot": {
        "x": 0.5,
        "y": 0.5
      }
    },
    "068.png": {
      "frame": {
        "x": 206,
        "y": 588,
        "w": 74,
        "h": 74
      },
      "rotated": false,
      "trimmed": true,
      "spriteSourceSize": {
        "x": 34,
        "y": 54,
        "w": 74,
        "h": 74
      },
      "sourceSize": {
        "w": 128,
        "h": 128
      },
      "pivot": {
        "x": 0.5,
        "y": 0.5
      }
    },
    "039.png": {
      "frame": {
        "x": 212,
        "y": 504,
        "w": 68,
        "h": 74
      },
      "rotated": false,
      "trimmed": true,
      "spriteSourceSize": {
        "x": 30,
        "y": 54,
        "w": 68,
        "h": 74
      },
      "sourceSize": {
        "w": 128,
        "h": 128
      },
      "pivot": {
        "x": 0.5,
        "y": 0.5
      }
    },
    "089.png": {
      "frame": {
        "x": 206,
        "y": 662,
        "w": 68,
        "h": 74
      },
      "rotated": false,
      "trimmed": true,
      "spriteSourceSize": {
        "x": 30,
        "y": 54,
        "w": 68,
        "h": 74
      },
      "sourceSize": {
        "w": 128,
        "h": 128
      },
      "pivot": {
        "x": 0.5,
        "y": 0.5
      }
    },
    "088.png": {
      "frame": {
        "x": 224,
        "y": 378,
        "w": 82,
        "h": 72
      },
      "rotated": false,
      "trimmed": true,
      "spriteSourceSize": {
        "x": 30,
        "y": 56,
        "w": 82,
        "h": 72
      },
      "sourceSize": {
        "w": 128,
        "h": 128
      },
      "pivot": {
        "x": 0.5,
        "y": 0.5
      }
    },
    "attack-11.png": {
      "frame": {
        "x": 224,
        "y": 450,
        "w": 76,
        "h": 52
      },
      "rotated": false,
      "trimmed": true,
      "spriteSourceSize": {
        "x": 24,
        "y": 76,
        "w": 76,
        "h": 52
      },
      "sourceSize": {
        "w": 128,
        "h": 128
      },
      "pivot": {
        "x": 0.5,
        "y": 0.5
      }
    },
    "087.png": {
      "frame": {
        "x": 296,
        "y": 284,
        "w": 70,
        "h": 72
      },
      "rotated": false,
      "trimmed": true,
      "spriteSourceSize": {
        "x": 30,
        "y": 56,
        "w": 70,
        "h": 72
      },
      "sourceSize": {
        "w": 128,
        "h": 128
      },
      "pivot": {
        "x": 0.5,
        "y": 0.5
      }
    },
    "084.png": {
      "frame": {
        "x": 332,
        "y": 166,
        "w": 68,
        "h": 72
      },
      "rotated": false,
      "trimmed": true,
      "spriteSourceSize": {
        "x": 30,
        "y": 56,
        "w": 68,
        "h": 72
      },
      "sourceSize": {
        "w": 128,
        "h": 128
      },
      "pivot": {
        "x": 0.5,
        "y": 0.5
      }
    },
    "085.png": {
      "frame": {
        "x": 388,
        "y": 82,
        "w": 68,
        "h": 72
      },
      "rotated": false,
      "trimmed": true,
      "spriteSourceSize": {
        "x": 30,
        "y": 56,
        "w": 68,
        "h": 72
      },
      "sourceSize": {
        "w": 128,
        "h": 128
      },
      "pivot": {
        "x": 0.5,
        "y": 0.5
      }
    },
    "086.png": {
      "frame": {
        "x": 424,
        "y": 0,
        "w": 68,
        "h": 72
      },
      "rotated": false,
      "trimmed": true,
      "spriteSourceSize": {
        "x": 30,
        "y": 56,
        "w": 68,
        "h": 72
      },
      "sourceSize": {
        "w": 128,
        "h": 128
      },
      "pivot": {
        "x": 0.5,
        "y": 0.5
      }
    },
    "death-6.png": {
      "frame": {
        "x": 0,
        "y": 1422,
        "w": 70,
        "h": 70
      },
      "rotated": false,
      "trimmed": true,
      "spriteSourceSize": {
        "x": 28,
        "y": 58,
        "w": 70,
        "h": 70
      },
      "sourceSize": {
        "w": 128,
        "h": 128
      },
      "pivot": {
        "x": 0.5,
        "y": 0.5
      }
    },
    "092.png": {
      "frame": {
        "x": 0,
        "y": 1492,
        "w": 68,
        "h": 70
      },
      "rotated": false,
      "trimmed": true,
      "spriteSourceSize": {
        "x": 30,
        "y": 58,
        "w": 68,
        "h": 70
      },
      "sourceSize": {
        "w": 128,
        "h": 128
      },
      "pivot": {
        "x": 0.5,
        "y": 0.5
      }
    },
    "attack-13.png": {
      "frame": {
        "x": 0,
        "y": 1562,
        "w": 68,
        "h": 70
      },
      "rotated": false,
      "trimmed": true,
      "spriteSourceSize": {
        "x": 28,
        "y": 58,
        "w": 68,
        "h": 70
      },
      "sourceSize": {
        "w": 128,
        "h": 128
      },
      "pivot": {
        "x": 0.5,
        "y": 0.5
      }
    },
    "attack-3.png": {
      "frame": {
        "x": 0,
        "y": 1632,
        "w": 68,
        "h": 70
      },
      "rotated": false,
      "trimmed": true,
      "spriteSourceSize": {
        "x": 30,
        "y": 58,
        "w": 68,
        "h": 70
      },
      "sourceSize": {
        "w": 128,
        "h": 128
      },
      "pivot": {
        "x": 0.5,
        "y": 0.5
      }
    },
    "death-5.png": {
      "frame": {
        "x": 0,
        "y": 1702,
        "w": 68,
        "h": 70
      },
      "rotated": false,
      "trimmed": true,
      "spriteSourceSize": {
        "x": 30,
        "y": 58,
        "w": 68,
        "h": 70
      },
      "sourceSize": {
        "w": 128,
        "h": 128
      },
      "pivot": {
        "x": 0.5,
        "y": 0.5
      }
    },
    "083.png": {
      "frame": {
        "x": 0,
        "y": 1772,
        "w": 68,
        "h": 68
      },
      "rotated": false,
      "trimmed": true,
      "spriteSourceSize": {
        "x": 30,
        "y": 60,
        "w": 68,
        "h": 68
      },
      "sourceSize": {
        "w": 128,
        "h": 128
      },
      "pivot": {
        "x": 0.5,
        "y": 0.5
      }
    },
    "attack-4.png": {
      "frame": {
        "x": 0,
        "y": 1840,
        "w": 68,
        "h": 68
      },
      "rotated": false,
      "trimmed": true,
      "spriteSourceSize": {
        "x": 30,
        "y": 60,
        "w": 68,
        "h": 68
      },
      "sourceSize": {
        "w": 128,
        "h": 128
      },
      "pivot": {
        "x": 0.5,
        "y": 0.5
      }
    },
    "death-4.png": {
      "frame": {
        "x": 0,
        "y": 1908,
        "w": 68,
        "h": 68
      },
      "rotated": false,
      "trimmed": true,
      "spriteSourceSize": {
        "x": 30,
        "y": 60,
        "w": 68,
        "h": 68
      },
      "sourceSize": {
        "w": 128,
        "h": 128
      },
      "pivot": {
        "x": 0.5,
        "y": 0.5
      }
    },
    "091.png": {
      "frame": {
        "x": 0,
        "y": 1976,
        "w": 68,
        "h": 60
      },
      "rotated": false,
      "trimmed": true,
      "spriteSourceSize": {
        "x": 30,
        "y": 68,
        "w": 68,
        "h": 60
      },
      "sourceSize": {
        "w": 128,
        "h": 128
      },
      "pivot": {
        "x": 0.5,
        "y": 0.5
      }
    },
    "attack-10.png": {
      "frame": {
        "x": 68,
        "y": 1492,
        "w": 72,
        "h": 56
      },
      "rotated": false,
      "trimmed": true,
      "spriteSourceSize": {
        "x": 26,
        "y": 72,
        "w": 72,
        "h": 56
      },
      "sourceSize": {
        "w": 128,
        "h": 128
      },
      "pivot": {
        "x": 0.5,
        "y": 0.5
      }
    },
    "attack-5.png": {
      "frame": {
        "x": 70,
        "y": 1422,
        "w": 72,
        "h": 56
      },
      "rotated": false,
      "trimmed": true,
      "spriteSourceSize": {
        "x": 24,
        "y": 72,
        "w": 72,
        "h": 56
      },
      "sourceSize": {
        "w": 128,
        "h": 128
      },
      "pivot": {
        "x": 0.5,
        "y": 0.5
      }
    },
    "death-7.png": {
      "frame": {
        "x": 90,
        "y": 1340,
        "w": 70,
        "h": 50
      },
      "rotated": false,
      "trimmed": true,
      "spriteSourceSize": {
        "x": 28,
        "y": 78,
        "w": 70,
        "h": 50
      },
      "sourceSize": {
        "w": 128,
        "h": 128
      },
      "pivot": {
        "x": 0.5,
        "y": 0.5
      }
    },
    "005.png": {
      "frame": {
        "x": 0,
        "y": 0,
        "w": 128,
        "h": 128
      },
      "rotated": false,
      "trimmed": false,
      "spriteSourceSize": {
        "x": 0,
        "y": 0,
        "w": 128,
        "h": 128
      },
      "sourceSize": {
        "w": 128,
        "h": 128
      },
      "pivot": {
        "x": 0.5,
        "y": 0.5
      }
    },
    "006.png": {
      "frame": {
        "x": 0,
        "y": 0,
        "w": 128,
        "h": 128
      },
      "rotated": false,
      "trimmed": false,
      "spriteSourceSize": {
        "x": 0,
        "y": 0,
        "w": 128,
        "h": 128
      },
      "sourceSize": {
        "w": 128,
        "h": 128
      },
      "pivot": {
        "x": 0.5,
        "y": 0.5
      }
    },
    "007.png": {
      "frame": {
        "x": 0,
        "y": 0,
        "w": 128,
        "h": 128
      },
      "rotated": false,
      "trimmed": false,
      "spriteSourceSize": {
        "x": 0,
        "y": 0,
        "w": 128,
        "h": 128
      },
      "sourceSize": {
        "w": 128,
        "h": 128
      },
      "pivot": {
        "x": 0.5,
        "y": 0.5
      }
    },
    "008.png": {
      "frame": {
        "x": 0,
        "y": 0,
        "w": 128,
        "h": 128
      },
      "rotated": false,
      "trimmed": false,
      "spriteSourceSize": {
        "x": 0,
        "y": 0,
        "w": 128,
        "h": 128
      },
      "sourceSize": {
        "w": 128,
        "h": 128
      },
      "pivot": {
        "x": 0.5,
        "y": 0.5
      }
    },
    "009.png": {
      "frame": {
        "x": 0,
        "y": 0,
        "w": 128,
        "h": 128
      },
      "rotated": false,
      "trimmed": false,
      "spriteSourceSize": {
        "x": 0,
        "y": 0,
        "w": 128,
        "h": 128
      },
      "sourceSize": {
        "w": 128,
        "h": 128
      },
      "pivot": {
        "x": 0.5,
        "y": 0.5
      }
    },
    "010.png": {
      "frame": {
        "x": 0,
        "y": 0,
        "w": 128,
        "h": 128
      },
      "rotated": false,
      "trimmed": false,
      "spriteSourceSize": {
        "x": 0,
        "y": 0,
        "w": 128,
        "h": 128
      },
      "sourceSize": {
        "w": 128,
        "h": 128
      },
      "pivot": {
        "x": 0.5,
        "y": 0.5
      }
    },
    "011.png": {
      "frame": {
        "x": 0,
        "y": 0,
        "w": 128,
        "h": 128
      },
      "rotated": false,
      "trimmed": false,
      "spriteSourceSize": {
        "x": 0,
        "y": 0,
        "w": 128,
        "h": 128
      },
      "sourceSize": {
        "w": 128,
        "h": 128
      },
      "pivot": {
        "x": 0.5,
        "y": 0.5
      }
    },
    "012.png": {
      "frame": {
        "x": 0,
        "y": 0,
        "w": 128,
        "h": 128
      },
      "rotated": false,
      "trimmed": false,
      "spriteSourceSize": {
        "x": 0,
        "y": 0,
        "w": 128,
        "h": 128
      },
      "sourceSize": {
        "w": 128,
        "h": 128
      },
      "pivot": {
        "x": 0.5,
        "y": 0.5
      }
    },
    "013.png": {
      "frame": {
        "x": 0,
        "y": 0,
        "w": 128,
        "h": 128
      },
      "rotated": false,
      "trimmed": false,
      "spriteSourceSize": {
        "x": 0,
        "y": 0,
        "w": 128,
        "h": 128
      },
      "sourceSize": {
        "w": 128,
        "h": 128
      },
      "pivot": {
        "x": 0.5,
        "y": 0.5
      }
    },
    "014.png": {
      "frame": {
        "x": 0,
        "y": 0,
        "w": 128,
        "h": 128
      },
      "rotated": false,
      "trimmed": false,
      "spriteSourceSize": {
        "x": 0,
        "y": 0,
        "w": 128,
        "h": 128
      },
      "sourceSize": {
        "w": 128,
        "h": 128
      },
      "pivot": {
        "x": 0.5,
        "y": 0.5
      }
    },
    "015.png": {
      "frame": {
        "x": 0,
        "y": 0,
        "w": 128,
        "h": 128
      },
      "rotated": false,
      "trimmed": false,
      "spriteSourceSize": {
        "x": 0,
        "y": 0,
        "w": 128,
        "h": 128
      },
      "sourceSize": {
        "w": 128,
        "h": 128
      },
      "pivot": {
        "x": 0.5,
        "y": 0.5
      }
    },
    "022.png": {
      "frame": {
        "x": 0,
        "y": 0,
        "w": 128,
        "h": 128
      },
      "rotated": false,
      "trimmed": false,
      "spriteSourceSize": {
        "x": 0,
        "y": 0,
        "w": 128,
        "h": 128
      },
      "sourceSize": {
        "w": 128,
        "h": 128
      },
      "pivot": {
        "x": 0.5,
        "y": 0.5
      }
    },
    "023.png": {
      "frame": {
        "x": 0,
        "y": 0,
        "w": 128,
        "h": 128
      },
      "rotated": false,
      "trimmed": false,
      "spriteSourceSize": {
        "x": 0,
        "y": 0,
        "w": 128,
        "h": 128
      },
      "sourceSize": {
        "w": 128,
        "h": 128
      },
      "pivot": {
        "x": 0.5,
        "y": 0.5
      }
    },
    "024.png": {
      "frame": {
        "x": 0,
        "y": 0,
        "w": 128,
        "h": 128
      },
      "rotated": false,
      "trimmed": false,
      "spriteSourceSize": {
        "x": 0,
        "y": 0,
        "w": 128,
        "h": 128
      },
      "sourceSize": {
        "w": 128,
        "h": 128
      },
      "pivot": {
        "x": 0.5,
        "y": 0.5
      }
    },
    "025.png": {
      "frame": {
        "x": 0,
        "y": 0,
        "w": 128,
        "h": 128
      },
      "rotated": false,
      "trimmed": false,
      "spriteSourceSize": {
        "x": 0,
        "y": 0,
        "w": 128,
        "h": 128
      },
      "sourceSize": {
        "w": 128,
        "h": 128
      },
      "pivot": {
        "x": 0.5,
        "y": 0.5
      }
    },
    "026.png": {
      "frame": {
        "x": 0,
        "y": 0,
        "w": 128,
        "h": 128
      },
      "rotated": false,
      "trimmed": false,
      "spriteSourceSize": {
        "x": 0,
        "y": 0,
        "w": 128,
        "h": 128
      },
      "sourceSize": {
        "w": 128,
        "h": 128
      },
      "pivot": {
        "x": 0.5,
        "y": 0.5
      }
    },
    "027.png": {
      "frame": {
        "x": 0,
        "y": 0,
        "w": 128,
        "h": 128
      },
      "rotated": false,
      "trimmed": false,
      "spriteSourceSize": {
        "x": 0,
        "y": 0,
        "w": 128,
        "h": 128
      },
      "sourceSize": {
        "w": 128,
        "h": 128
      },
      "pivot": {
        "x": 0.5,
        "y": 0.5
      }
    },
    "028.png": {
      "frame": {
        "x": 0,
        "y": 0,
        "w": 128,
        "h": 128
      },
      "rotated": false,
      "trimmed": false,
      "spriteSourceSize": {
        "x": 0,
        "y": 0,
        "w": 128,
        "h": 128
      },
      "sourceSize": {
        "w": 128,
        "h": 128
      },
      "pivot": {
        "x": 0.5,
        "y": 0.5
      }
    },
    "029.png": {
      "frame": {
        "x": 0,
        "y": 0,
        "w": 128,
        "h": 128
      },
      "rotated": false,
      "trimmed": false,
      "spriteSourceSize": {
        "x": 0,
        "y": 0,
        "w": 128,
        "h": 128
      },
      "sourceSize": {
        "w": 128,
        "h": 128
      },
      "pivot": {
        "x": 0.5,
        "y": 0.5
      }
    },
    "030.png": {
      "frame": {
        "x": 0,
        "y": 0,
        "w": 128,
        "h": 128
      },
      "rotated": false,
      "trimmed": false,
      "spriteSourceSize": {
        "x": 0,
        "y": 0,
        "w": 128,
        "h": 128
      },
      "sourceSize": {
        "w": 128,
        "h": 128
      },
      "pivot": {
        "x": 0.5,
        "y": 0.5
      }
    },
    "031.png": {
      "frame": {
        "x": 0,
        "y": 0,
        "w": 128,
        "h": 128
      },
      "rotated": false,
      "trimmed": false,
      "spriteSourceSize": {
        "x": 0,
        "y": 0,
        "w": 128,
        "h": 128
      },
      "sourceSize": {
        "w": 128,
        "h": 128
      },
      "pivot": {
        "x": 0.5,
        "y": 0.5
      }
    },
    "040.png": {
      "frame": {
        "x": 0,
        "y": 0,
        "w": 128,
        "h": 128
      },
      "rotated": false,
      "trimmed": false,
      "spriteSourceSize": {
        "x": 0,
        "y": 0,
        "w": 128,
        "h": 128
      },
      "sourceSize": {
        "w": 128,
        "h": 128
      },
      "pivot": {
        "x": 0.5,
        "y": 0.5
      }
    },
    "041.png": {
      "frame": {
        "x": 0,
        "y": 0,
        "w": 128,
        "h": 128
      },
      "rotated": false,
      "trimmed": false,
      "spriteSourceSize": {
        "x": 0,
        "y": 0,
        "w": 128,
        "h": 128
      },
      "sourceSize": {
        "w": 128,
        "h": 128
      },
      "pivot": {
        "x": 0.5,
        "y": 0.5
      }
    },
    "042.png": {
      "frame": {
        "x": 0,
        "y": 0,
        "w": 128,
        "h": 128
      },
      "rotated": false,
      "trimmed": false,
      "spriteSourceSize": {
        "x": 0,
        "y": 0,
        "w": 128,
        "h": 128
      },
      "sourceSize": {
        "w": 128,
        "h": 128
      },
      "pivot": {
        "x": 0.5,
        "y": 0.5
      }
    },
    "043.png": {
      "frame": {
        "x": 0,
        "y": 0,
        "w": 128,
        "h": 128
      },
      "rotated": false,
      "trimmed": false,
      "spriteSourceSize": {
        "x": 0,
        "y": 0,
        "w": 128,
        "h": 128
      },
      "sourceSize": {
        "w": 128,
        "h": 128
      },
      "pivot": {
        "x": 0.5,
        "y": 0.5
      }
    },
    "044.png": {
      "frame": {
        "x": 0,
        "y": 0,
        "w": 128,
        "h": 128
      },
      "rotated": false,
      "trimmed": false,
      "spriteSourceSize": {
        "x": 0,
        "y": 0,
        "w": 128,
        "h": 128
      },
      "sourceSize": {
        "w": 128,
        "h": 128
      },
      "pivot": {
        "x": 0.5,
        "y": 0.5
      }
    },
    "045.png": {
      "frame": {
        "x": 0,
        "y": 0,
        "w": 128,
        "h": 128
      },
      "rotated": false,
      "trimmed": false,
      "spriteSourceSize": {
        "x": 0,
        "y": 0,
        "w": 128,
        "h": 128
      },
      "sourceSize": {
        "w": 128,
        "h": 128
      },
      "pivot": {
        "x": 0.5,
        "y": 0.5
      }
    },
    "046.png": {
      "frame": {
        "x": 0,
        "y": 0,
        "w": 128,
        "h": 128
      },
      "rotated": false,
      "trimmed": false,
      "spriteSourceSize": {
        "x": 0,
        "y": 0,
        "w": 128,
        "h": 128
      },
      "sourceSize": {
        "w": 128,
        "h": 128
      },
      "pivot": {
        "x": 0.5,
        "y": 0.5
      }
    },
    "047.png": {
      "frame": {
        "x": 0,
        "y": 0,
        "w": 128,
        "h": 128
      },
      "rotated": false,
      "trimmed": false,
      "spriteSourceSize": {
        "x": 0,
        "y": 0,
        "w": 128,
        "h": 128
      },
      "sourceSize": {
        "w": 128,
        "h": 128
      },
      "pivot": {
        "x": 0.5,
        "y": 0.5
      }
    },
    "060.png": {
      "frame": {
        "x": 0,
        "y": 0,
        "w": 128,
        "h": 128
      },
      "rotated": false,
      "trimmed": false,
      "spriteSourceSize": {
        "x": 0,
        "y": 0,
        "w": 128,
        "h": 128
      },
      "sourceSize": {
        "w": 128,
        "h": 128
      },
      "pivot": {
        "x": 0.5,
        "y": 0.5
      }
    },
    "061.png": {
      "frame": {
        "x": 0,
        "y": 0,
        "w": 128,
        "h": 128
      },
      "rotated": false,
      "trimmed": false,
      "spriteSourceSize": {
        "x": 0,
        "y": 0,
        "w": 128,
        "h": 128
      },
      "sourceSize": {
        "w": 128,
        "h": 128
      },
      "pivot": {
        "x": 0.5,
        "y": 0.5
      }
    },
    "062.png": {
      "frame": {
        "x": 0,
        "y": 0,
        "w": 128,
        "h": 128
      },
      "rotated": false,
      "trimmed": false,
      "spriteSourceSize": {
        "x": 0,
        "y": 0,
        "w": 128,
        "h": 128
      },
      "sourceSize": {
        "w": 128,
        "h": 128
      },
      "pivot": {
        "x": 0.5,
        "y": 0.5
      }
    },
    "063.png": {
      "frame": {
        "x": 0,
        "y": 0,
        "w": 128,
        "h": 128
      },
      "rotated": false,
      "trimmed": false,
      "spriteSourceSize": {
        "x": 0,
        "y": 0,
        "w": 128,
        "h": 128
      },
      "sourceSize": {
        "w": 128,
        "h": 128
      },
      "pivot": {
        "x": 0.5,
        "y": 0.5
      }
    },
    "072.png": {
      "frame": {
        "x": 0,
        "y": 0,
        "w": 128,
        "h": 128
      },
      "rotated": false,
      "trimmed": false,
      "spriteSourceSize": {
        "x": 0,
        "y": 0,
        "w": 128,
        "h": 128
      },
      "sourceSize": {
        "w": 128,
        "h": 128
      },
      "pivot": {
        "x": 0.5,
        "y": 0.5
      }
    },
    "073.png": {
      "frame": {
        "x": 0,
        "y": 0,
        "w": 128,
        "h": 128
      },
      "rotated": false,
      "trimmed": false,
      "spriteSourceSize": {
        "x": 0,
        "y": 0,
        "w": 128,
        "h": 128
      },
      "sourceSize": {
        "w": 128,
        "h": 128
      },
      "pivot": {
        "x": 0.5,
        "y": 0.5
      }
    },
    "074.png": {
      "frame": {
        "x": 0,
        "y": 0,
        "w": 128,
        "h": 128
      },
      "rotated": false,
      "trimmed": false,
      "spriteSourceSize": {
        "x": 0,
        "y": 0,
        "w": 128,
        "h": 128
      },
      "sourceSize": {
        "w": 128,
        "h": 128
      },
      "pivot": {
        "x": 0.5,
        "y": 0.5
      }
    },
    "075.png": {
      "frame": {
        "x": 0,
        "y": 0,
        "w": 128,
        "h": 128
      },
      "rotated": false,
      "trimmed": false,
      "spriteSourceSize": {
        "x": 0,
        "y": 0,
        "w": 128,
        "h": 128
      },
      "sourceSize": {
        "w": 128,
        "h": 128
      },
      "pivot": {
        "x": 0.5,
        "y": 0.5
      }
    },
    "076.png": {
      "frame": {
        "x": 0,
        "y": 0,
        "w": 128,
        "h": 128
      },
      "rotated": false,
      "trimmed": false,
      "spriteSourceSize": {
        "x": 0,
        "y": 0,
        "w": 128,
        "h": 128
      },
      "sourceSize": {
        "w": 128,
        "h": 128
      },
      "pivot": {
        "x": 0.5,
        "y": 0.5
      }
    },
    "077.png": {
      "frame": {
        "x": 0,
        "y": 0,
        "w": 128,
        "h": 128
      },
      "rotated": false,
      "trimmed": false,
      "spriteSourceSize": {
        "x": 0,
        "y": 0,
        "w": 128,
        "h": 128
      },
      "sourceSize": {
        "w": 128,
        "h": 128
      },
      "pivot": {
        "x": 0.5,
        "y": 0.5
      }
    },
    "078.png": {
      "frame": {
        "x": 0,
        "y": 0,
        "w": 128,
        "h": 128
      },
      "rotated": false,
      "trimmed": false,
      "spriteSourceSize": {
        "x": 0,
        "y": 0,
        "w": 128,
        "h": 128
      },
      "sourceSize": {
        "w": 128,
        "h": 128
      },
      "pivot": {
        "x": 0.5,
        "y": 0.5
      }
    },
    "079.png": {
      "frame": {
        "x": 0,
        "y": 0,
        "w": 128,
        "h": 128
      },
      "rotated": false,
      "trimmed": false,
      "spriteSourceSize": {
        "x": 0,
        "y": 0,
        "w": 128,
        "h": 128
      },
      "sourceSize": {
        "w": 128,
        "h": 128
      },
      "pivot": {
        "x": 0.5,
        "y": 0.5
      }
    },
    "100.png": {
      "frame": {
        "x": 0,
        "y": 0,
        "w": 128,
        "h": 128
      },
      "rotated": false,
      "trimmed": false,
      "spriteSourceSize": {
        "x": 0,
        "y": 0,
        "w": 128,
        "h": 128
      },
      "sourceSize": {
        "w": 128,
        "h": 128
      },
      "pivot": {
        "x": 0.5,
        "y": 0.5
      }
    },
    "101.png": {
      "frame": {
        "x": 0,
        "y": 0,
        "w": 128,
        "h": 128
      },
      "rotated": false,
      "trimmed": false,
      "spriteSourceSize": {
        "x": 0,
        "y": 0,
        "w": 128,
        "h": 128
      },
      "sourceSize": {
        "w": 128,
        "h": 128
      },
      "pivot": {
        "x": 0.5,
        "y": 0.5
      }
    },
    "102.png": {
      "frame": {
        "x": 0,
        "y": 0,
        "w": 128,
        "h": 128
      },
      "rotated": false,
      "trimmed": false,
      "spriteSourceSize": {
        "x": 0,
        "y": 0,
        "w": 128,
        "h": 128
      },
      "sourceSize": {
        "w": 128,
        "h": 128
      },
      "pivot": {
        "x": 0.5,
        "y": 0.5
      }
    },
    "103.png": {
      "frame": {
        "x": 0,
        "y": 0,
        "w": 128,
        "h": 128
      },
      "rotated": false,
      "trimmed": false,
      "spriteSourceSize": {
        "x": 0,
        "y": 0,
        "w": 128,
        "h": 128
      },
      "sourceSize": {
        "w": 128,
        "h": 128
      },
      "pivot": {
        "x": 0.5,
        "y": 0.5
      }
    },
    "104.png": {
      "frame": {
        "x": 0,
        "y": 0,
        "w": 128,
        "h": 128
      },
      "rotated": false,
      "trimmed": false,
      "spriteSourceSize": {
        "x": 0,
        "y": 0,
        "w": 128,
        "h": 128
      },
      "sourceSize": {
        "w": 128,
        "h": 128
      },
      "pivot": {
        "x": 0.5,
        "y": 0.5
      }
    },
    "105.png": {
      "frame": {
        "x": 0,
        "y": 0,
        "w": 128,
        "h": 128
      },
      "rotated": false,
      "trimmed": false,
      "spriteSourceSize": {
        "x": 0,
        "y": 0,
        "w": 128,
        "h": 128
      },
      "sourceSize": {
        "w": 128,
        "h": 128
      },
      "pivot": {
        "x": 0.5,
        "y": 0.5
      }
    },
    "106.png": {
      "frame": {
        "x": 0,
        "y": 0,
        "w": 128,
        "h": 128
      },
      "rotated": false,
      "trimmed": false,
      "spriteSourceSize": {
        "x": 0,
        "y": 0,
        "w": 128,
        "h": 128
      },
      "sourceSize": {
        "w": 128,
        "h": 128
      },
      "pivot": {
        "x": 0.5,
        "y": 0.5
      }
    },
    "107.png": {
      "frame": {
        "x": 0,
        "y": 0,
        "w": 128,
        "h": 128
      },
      "rotated": false,
      "trimmed": false,
      "spriteSourceSize": {
        "x": 0,
        "y": 0,
        "w": 128,
        "h": 128
      },
      "sourceSize": {
        "w": 128,
        "h": 128
      },
      "pivot": {
        "x": 0.5,
        "y": 0.5
      }
    },
    "108.png": {
      "frame": {
        "x": 0,
        "y": 0,
        "w": 128,
        "h": 128
      },
      "rotated": false,
      "trimmed": false,
      "spriteSourceSize": {
        "x": 0,
        "y": 0,
        "w": 128,
        "h": 128
      },
      "sourceSize": {
        "w": 128,
        "h": 128
      },
      "pivot": {
        "x": 0.5,
        "y": 0.5
      }
    },
    "109.png": {
      "frame": {
        "x": 0,
        "y": 0,
        "w": 128,
        "h": 128
      },
      "rotated": false,
      "trimmed": false,
      "spriteSourceSize": {
        "x": 0,
        "y": 0,
        "w": 128,
        "h": 128
      },
      "sourceSize": {
        "w": 128,
        "h": 128
      },
      "pivot": {
        "x": 0.5,
        "y": 0.5
      }
    },
    "110.png": {
      "frame": {
        "x": 0,
        "y": 0,
        "w": 128,
        "h": 128
      },
      "rotated": false,
      "trimmed": false,
      "spriteSourceSize": {
        "x": 0,
        "y": 0,
        "w": 128,
        "h": 128
      },
      "sourceSize": {
        "w": 128,
        "h": 128
      },
      "pivot": {
        "x": 0.5,
        "y": 0.5
      }
    },
    "111.png": {
      "frame": {
        "x": 0,
        "y": 0,
        "w": 128,
        "h": 128
      },
      "rotated": false,
      "trimmed": false,
      "spriteSourceSize": {
        "x": 0,
        "y": 0,
        "w": 128,
        "h": 128
      },
      "sourceSize": {
        "w": 128,
        "h": 128
      },
      "pivot": {
        "x": 0.5,
        "y": 0.5
      }
    },
    "123.png": {
      "frame": {
        "x": 0,
        "y": 0,
        "w": 128,
        "h": 128
      },
      "rotated": false,
      "trimmed": false,
      "spriteSourceSize": {
        "x": 0,
        "y": 0,
        "w": 128,
        "h": 128
      },
      "sourceSize": {
        "w": 128,
        "h": 128
      },
      "pivot": {
        "x": 0.5,
        "y": 0.5
      }
    },
    "124.png": {
      "frame": {
        "x": 0,
        "y": 0,
        "w": 128,
        "h": 128
      },
      "rotated": false,
      "trimmed": false,
      "spriteSourceSize": {
        "x": 0,
        "y": 0,
        "w": 128,
        "h": 128
      },
      "sourceSize": {
        "w": 128,
        "h": 128
      },
      "pivot": {
        "x": 0.5,
        "y": 0.5
      }
    },
    "125.png": {
      "frame": {
        "x": 0,
        "y": 0,
        "w": 128,
        "h": 128
      },
      "rotated": false,
      "trimmed": false,
      "spriteSourceSize": {
        "x": 0,
        "y": 0,
        "w": 128,
        "h": 128
      },
      "sourceSize": {
        "w": 128,
        "h": 128
      },
      "pivot": {
        "x": 0.5,
        "y": 0.5
      }
    },
    "126.png": {
      "frame": {
        "x": 0,
        "y": 0,
        "w": 128,
        "h": 128
      },
      "rotated": false,
      "trimmed": false,
      "spriteSourceSize": {
        "x": 0,
        "y": 0,
        "w": 128,
        "h": 128
      },
      "sourceSize": {
        "w": 128,
        "h": 128
      },
      "pivot": {
        "x": 0.5,
        "y": 0.5
      }
    },
    "127.png": {
      "frame": {
        "x": 0,
        "y": 0,
        "w": 128,
        "h": 128
      },
      "rotated": false,
      "trimmed": false,
      "spriteSourceSize": {
        "x": 0,
        "y": 0,
        "w": 128,
        "h": 128
      },
      "sourceSize": {
        "w": 128,
        "h": 128
      },
      "pivot": {
        "x": 0.5,
        "y": 0.5
      }
    },
    "134.png": {
      "frame": {
        "x": 0,
        "y": 0,
        "w": 128,
        "h": 128
      },
      "rotated": false,
      "trimmed": false,
      "spriteSourceSize": {
        "x": 0,
        "y": 0,
        "w": 128,
        "h": 128
      },
      "sourceSize": {
        "w": 128,
        "h": 128
      },
      "pivot": {
        "x": 0.5,
        "y": 0.5
      }
    },
    "135.png": {
      "frame": {
        "x": 0,
        "y": 0,
        "w": 128,
        "h": 128
      },
      "rotated": false,
      "trimmed": false,
      "spriteSourceSize": {
        "x": 0,
        "y": 0,
        "w": 128,
        "h": 128
      },
      "sourceSize": {
        "w": 128,
        "h": 128
      },
      "pivot": {
        "x": 0.5,
        "y": 0.5
      }
    },
    "136.png": {
      "frame": {
        "x": 0,
        "y": 0,
        "w": 128,
        "h": 128
      },
      "rotated": false,
      "trimmed": false,
      "spriteSourceSize": {
        "x": 0,
        "y": 0,
        "w": 128,
        "h": 128
      },
      "sourceSize": {
        "w": 128,
        "h": 128
      },
      "pivot": {
        "x": 0.5,
        "y": 0.5
      }
    },
    "137.png": {
      "frame": {
        "x": 0,
        "y": 0,
        "w": 128,
        "h": 128
      },
      "rotated": false,
      "trimmed": false,
      "spriteSourceSize": {
        "x": 0,
        "y": 0,
        "w": 128,
        "h": 128
      },
      "sourceSize": {
        "w": 128,
        "h": 128
      },
      "pivot": {
        "x": 0.5,
        "y": 0.5
      }
    },
    "138.png": {
      "frame": {
        "x": 0,
        "y": 0,
        "w": 128,
        "h": 128
      },
      "rotated": false,
      "trimmed": false,
      "spriteSourceSize": {
        "x": 0,
        "y": 0,
        "w": 128,
        "h": 128
      },
      "sourceSize": {
        "w": 128,
        "h": 128
      },
      "pivot": {
        "x": 0.5,
        "y": 0.5
      }
    },
    "139.png": {
      "frame": {
        "x": 0,
        "y": 0,
        "w": 128,
        "h": 128
      },
      "rotated": false,
      "trimmed": false,
      "spriteSourceSize": {
        "x": 0,
        "y": 0,
        "w": 128,
        "h": 128
      },
      "sourceSize": {
        "w": 128,
        "h": 128
      },
      "pivot": {
        "x": 0.5,
        "y": 0.5
      }
    },
    "140.png": {
      "frame": {
        "x": 0,
        "y": 0,
        "w": 128,
        "h": 128
      },
      "rotated": false,
      "trimmed": false,
      "spriteSourceSize": {
        "x": 0,
        "y": 0,
        "w": 128,
        "h": 128
      },
      "sourceSize": {
        "w": 128,
        "h": 128
      },
      "pivot": {
        "x": 0.5,
        "y": 0.5
      }
    },
    "141.png": {
      "frame": {
        "x": 0,
        "y": 0,
        "w": 128,
        "h": 128
      },
      "rotated": false,
      "trimmed": false,
      "spriteSourceSize": {
        "x": 0,
        "y": 0,
        "w": 128,
        "h": 128
      },
      "sourceSize": {
        "w": 128,
        "h": 128
      },
      "pivot": {
        "x": 0.5,
        "y": 0.5
      }
    },
    "142.png": {
      "frame": {
        "x": 0,
        "y": 0,
        "w": 128,
        "h": 128
      },
      "rotated": false,
      "trimmed": false,
      "spriteSourceSize": {
        "x": 0,
        "y": 0,
        "w": 128,
        "h": 128
      },
      "sourceSize": {
        "w": 128,
        "h": 128
      },
      "pivot": {
        "x": 0.5,
        "y": 0.5
      }
    },
    "143.png": {
      "frame": {
        "x": 0,
        "y": 0,
        "w": 128,
        "h": 128
      },
      "rotated": false,
      "trimmed": false,
      "spriteSourceSize": {
        "x": 0,
        "y": 0,
        "w": 128,
        "h": 128
      },
      "sourceSize": {
        "w": 128,
        "h": 128
      },
      "pivot": {
        "x": 0.5,
        "y": 0.5
      }
    },
    "150.png": {
      "frame": {
        "x": 0,
        "y": 0,
        "w": 128,
        "h": 128
      },
      "rotated": false,
      "trimmed": false,
      "spriteSourceSize": {
        "x": 0,
        "y": 0,
        "w": 128,
        "h": 128
      },
      "sourceSize": {
        "w": 128,
        "h": 128
      },
      "pivot": {
        "x": 0.5,
        "y": 0.5
      }
    },
    "151.png": {
      "frame": {
        "x": 0,
        "y": 0,
        "w": 128,
        "h": 128
      },
      "rotated": false,
      "trimmed": false,
      "spriteSourceSize": {
        "x": 0,
        "y": 0,
        "w": 128,
        "h": 128
      },
      "sourceSize": {
        "w": 128,
        "h": 128
      },
      "pivot": {
        "x": 0.5,
        "y": 0.5
      }
    },
    "152.png": {
      "frame": {
        "x": 0,
        "y": 0,
        "w": 128,
        "h": 128
      },
      "rotated": false,
      "trimmed": false,
      "spriteSourceSize": {
        "x": 0,
        "y": 0,
        "w": 128,
        "h": 128
      },
      "sourceSize": {
        "w": 128,
        "h": 128
      },
      "pivot": {
        "x": 0.5,
        "y": 0.5
      }
    },
    "153.png": {
      "frame": {
        "x": 0,
        "y": 0,
        "w": 128,
        "h": 128
      },
      "rotated": false,
      "trimmed": false,
      "spriteSourceSize": {
        "x": 0,
        "y": 0,
        "w": 128,
        "h": 128
      },
      "sourceSize": {
        "w": 128,
        "h": 128
      },
      "pivot": {
        "x": 0.5,
        "y": 0.5
      }
    },
    "154.png": {
      "frame": {
        "x": 0,
        "y": 0,
        "w": 128,
        "h": 128
      },
      "rotated": false,
      "trimmed": false,
      "spriteSourceSize": {
        "x": 0,
        "y": 0,
        "w": 128,
        "h": 128
      },
      "sourceSize": {
        "w": 128,
        "h": 128
      },
      "pivot": {
        "x": 0.5,
        "y": 0.5
      }
    },
    "155.png": {
      "frame": {
        "x": 0,
        "y": 0,
        "w": 128,
        "h": 128
      },
      "rotated": false,
      "trimmed": false,
      "spriteSourceSize": {
        "x": 0,
        "y": 0,
        "w": 128,
        "h": 128
      },
      "sourceSize": {
        "w": 128,
        "h": 128
      },
      "pivot": {
        "x": 0.5,
        "y": 0.5
      }
    },
    "156.png": {
      "frame": {
        "x": 0,
        "y": 0,
        "w": 128,
        "h": 128
      },
      "rotated": false,
      "trimmed": false,
      "spriteSourceSize": {
        "x": 0,
        "y": 0,
        "w": 128,
        "h": 128
      },
      "sourceSize": {
        "w": 128,
        "h": 128
      },
      "pivot": {
        "x": 0.5,
        "y": 0.5
      }
    },
    "157.png": {
      "frame": {
        "x": 0,
        "y": 0,
        "w": 128,
        "h": 128
      },
      "rotated": false,
      "trimmed": false,
      "spriteSourceSize": {
        "x": 0,
        "y": 0,
        "w": 128,
        "h": 128
      },
      "sourceSize": {
        "w": 128,
        "h": 128
      },
      "pivot": {
        "x": 0.5,
        "y": 0.5
      }
    },
    "158.png": {
      "frame": {
        "x": 0,
        "y": 0,
        "w": 128,
        "h": 128
      },
      "rotated": false,
      "trimmed": false,
      "spriteSourceSize": {
        "x": 0,
        "y": 0,
        "w": 128,
        "h": 128
      },
      "sourceSize": {
        "w": 128,
        "h": 128
      },
      "pivot": {
        "x": 0.5,
        "y": 0.5
      }
    },
    "159.png": {
      "frame": {
        "x": 0,
        "y": 0,
        "w": 128,
        "h": 128
      },
      "rotated": false,
      "trimmed": false,
      "spriteSourceSize": {
        "x": 0,
        "y": 0,
        "w": 128,
        "h": 128
      },
      "sourceSize": {
        "w": 128,
        "h": 128
      },
      "pivot": {
        "x": 0.5,
        "y": 0.5
      }
    },
    "167.png": {
      "frame": {
        "x": 0,
        "y": 0,
        "w": 128,
        "h": 128
      },
      "rotated": false,
      "trimmed": false,
      "spriteSourceSize": {
        "x": 0,
        "y": 0,
        "w": 128,
        "h": 128
      },
      "sourceSize": {
        "w": 128,
        "h": 128
      },
      "pivot": {
        "x": 0.5,
        "y": 0.5
      }
    },
    "168.png": {
      "frame": {
        "x": 0,
        "y": 0,
        "w": 128,
        "h": 128
      },
      "rotated": false,
      "trimmed": false,
      "spriteSourceSize": {
        "x": 0,
        "y": 0,
        "w": 128,
        "h": 128
      },
      "sourceSize": {
        "w": 128,
        "h": 128
      },
      "pivot": {
        "x": 0.5,
        "y": 0.5
      }
    },
    "169.png": {
      "frame": {
        "x": 0,
        "y": 0,
        "w": 128,
        "h": 128
      },
      "rotated": false,
      "trimmed": false,
      "spriteSourceSize": {
        "x": 0,
        "y": 0,
        "w": 128,
        "h": 128
      },
      "sourceSize": {
        "w": 128,
        "h": 128
      },
      "pivot": {
        "x": 0.5,
        "y": 0.5
      }
    },
    "170.png": {
      "frame": {
        "x": 0,
        "y": 0,
        "w": 128,
        "h": 128
      },
      "rotated": false,
      "trimmed": false,
      "spriteSourceSize": {
        "x": 0,
        "y": 0,
        "w": 128,
        "h": 128
      },
      "sourceSize": {
        "w": 128,
        "h": 128
      },
      "pivot": {
        "x": 0.5,
        "y": 0.5
      }
    },
    "171.png": {
      "frame": {
        "x": 0,
        "y": 0,
        "w": 128,
        "h": 128
      },
      "rotated": false,
      "trimmed": false,
      "spriteSourceSize": {
        "x": 0,
        "y": 0,
        "w": 128,
        "h": 128
      },
      "sourceSize": {
        "w": 128,
        "h": 128
      },
      "pivot": {
        "x": 0.5,
        "y": 0.5
      }
    },
    "172.png": {
      "frame": {
        "x": 0,
        "y": 0,
        "w": 128,
        "h": 128
      },
      "rotated": false,
      "trimmed": false,
      "spriteSourceSize": {
        "x": 0,
        "y": 0,
        "w": 128,
        "h": 128
      },
      "sourceSize": {
        "w": 128,
        "h": 128
      },
      "pivot": {
        "x": 0.5,
        "y": 0.5
      }
    },
    "173.png": {
      "frame": {
        "x": 0,
        "y": 0,
        "w": 128,
        "h": 128
      },
      "rotated": false,
      "trimmed": false,
      "spriteSourceSize": {
        "x": 0,
        "y": 0,
        "w": 128,
        "h": 128
      },
      "sourceSize": {
        "w": 128,
        "h": 128
      },
      "pivot": {
        "x": 0.5,
        "y": 0.5
      }
    },
    "174.png": {
      "frame": {
        "x": 0,
        "y": 0,
        "w": 128,
        "h": 128
      },
      "rotated": false,
      "trimmed": false,
      "spriteSourceSize": {
        "x": 0,
        "y": 0,
        "w": 128,
        "h": 128
      },
      "sourceSize": {
        "w": 128,
        "h": 128
      },
      "pivot": {
        "x": 0.5,
        "y": 0.5
      }
    },
    "175.png": {
      "frame": {
        "x": 0,
        "y": 0,
        "w": 128,
        "h": 128
      },
      "rotated": false,
      "trimmed": false,
      "spriteSourceSize": {
        "x": 0,
        "y": 0,
        "w": 128,
        "h": 128
      },
      "sourceSize": {
        "w": 128,
        "h": 128
      },
      "pivot": {
        "x": 0.5,
        "y": 0.5
      }
    },
    "071.png": {
      "frame": {
        "x": 0,
        "y": 852,
        "w": 68,
        "h": 82
      },
      "rotated": false,
      "trimmed": true,
      "spriteSourceSize": {
        "x": 30,
        "y": 46,
        "w": 68,
        "h": 82
      },
      "sourceSize": {
        "w": 128,
        "h": 128
      },
      "pivot": {
        "x": 0.5,
        "y": 0.5
      }
    },
    "080.png": {
      "frame": {
        "x": 0,
        "y": 852,
        "w": 68,
        "h": 82
      },
      "rotated": false,
      "trimmed": true,
      "spriteSourceSize": {
        "x": 30,
        "y": 46,
        "w": 68,
        "h": 82
      },
      "sourceSize": {
        "w": 128,
        "h": 128
      },
      "pivot": {
        "x": 0.5,
        "y": 0.5
      }
    },
    "095.png": {
      "frame": {
        "x": 0,
        "y": 852,
        "w": 68,
        "h": 82
      },
      "rotated": false,
      "trimmed": true,
      "spriteSourceSize": {
        "x": 30,
        "y": 46,
        "w": 68,
        "h": 82
      },
      "sourceSize": {
        "w": 128,
        "h": 128
      },
      "pivot": {
        "x": 0.5,
        "y": 0.5
      }
    },
    "096.png": {
      "frame": {
        "x": 0,
        "y": 852,
        "w": 68,
        "h": 82
      },
      "rotated": false,
      "trimmed": true,
      "spriteSourceSize": {
        "x": 30,
        "y": 46,
        "w": 68,
        "h": 82
      },
      "sourceSize": {
        "w": 128,
        "h": 128
      },
      "pivot": {
        "x": 0.5,
        "y": 0.5
      }
    },
    "128.png": {
      "frame": {
        "x": 0,
        "y": 852,
        "w": 68,
        "h": 82
      },
      "rotated": false,
      "trimmed": true,
      "spriteSourceSize": {
        "x": 30,
        "y": 46,
        "w": 68,
        "h": 82
      },
      "sourceSize": {
        "w": 128,
        "h": 128
      },
      "pivot": {
        "x": 0.5,
        "y": 0.5
      }
    },
    "attack-1.png": {
      "frame": {
        "x": 0,
        "y": 852,
        "w": 68,
        "h": 82
      },
      "rotated": false,
      "trimmed": true,
      "spriteSourceSize": {
        "x": 30,
        "y": 46,
        "w": 68,
        "h": 82
      },
      "sourceSize": {
        "w": 128,
        "h": 128
      },
      "pivot": {
        "x": 0.5,
        "y": 0.5
      }
    },
    "death-1.png": {
      "frame": {
        "x": 0,
        "y": 852,
        "w": 68,
        "h": 82
      },
      "rotated": false,
      "trimmed": true,
      "spriteSourceSize": {
        "x": 30,
        "y": 46,
        "w": 68,
        "h": 82
      },
      "sourceSize": {
        "w": 128,
        "h": 128
      },
      "pivot": {
        "x": 0.5,
        "y": 0.5
      }
    },
    "idle-3.png": {
      "frame": {
        "x": 0,
        "y": 852,
        "w": 68,
        "h": 82
      },
      "rotated": false,
      "trimmed": true,
      "spriteSourceSize": {
        "x": 30,
        "y": 46,
        "w": 68,
        "h": 82
      },
      "sourceSize": {
        "w": 128,
        "h": 128
      },
      "pivot": {
        "x": 0.5,
        "y": 0.5
      }
    },
    "059.png": {
      "frame": {
        "x": 256,
        "y": 202,
        "w": 76,
        "h": 82
      },
      "rotated": false,
      "trimmed": true,
      "spriteSourceSize": {
        "x": 30,
        "y": 46,
        "w": 76,
        "h": 82
      },
      "sourceSize": {
        "w": 128,
        "h": 128
      },
      "pivot": {
        "x": 0.5,
        "y": 0.5
      }
    },
    "064.png": {
      "frame": {
        "x": 256,
        "y": 202,
        "w": 76,
        "h": 82
      },
      "rotated": false,
      "trimmed": true,
      "spriteSourceSize": {
        "x": 30,
        "y": 46,
        "w": 76,
        "h": 82
      },
      "sourceSize": {
        "w": 128,
        "h": 128
      },
      "pivot": {
        "x": 0.5,
        "y": 0.5
      }
    },
    "attack-12.png": {
      "frame": {
        "x": 68,
        "y": 1492,
        "w": 72,
        "h": 56
      },
      "rotated": false,
      "trimmed": true,
      "spriteSourceSize": {
        "x": 26,
        "y": 72,
        "w": 72,
        "h": 56
      },
      "sourceSize": {
        "w": 128,
        "h": 128
      },
      "pivot": {
        "x": 0.5,
        "y": 0.5
      }
    }
  },
  "meta": {
    "app": "http://free-tex-packer.com",
    "version": "0.6.7",
    "image": "goblinKing.png",
    "format": "RGBA8888",
    "size": {
      "w": 492,
      "h": 2036
    },
    "scale": 1
  }
}